docdown/__init__.py
docdown/docdown.py
docdown/include.py
docdown/links.py
docdown/media.py
docdown/media_carousels.py
docdown/note_blocks.py
docdown/platform_section.py
docdown/scoped_code_tabs.py
docdown/sequence.py
docdown/fenced_code_tabs/README.md
docdown/fenced_code_tabs/__init__.py
docdown/fenced_code_tabs/base-template.html
docdown/fenced_code_tabs/bootstrap3-template.html
docdown/fenced_code_tabs/bootstrap4-template.html
docdown/fenced_code_tabs/bootstrap5-template.html
docdown/fenced_code_tabs/default-template.html
docdown/fenced_code_tabs/tab.py
docdown/fenced_code_tabs/util.py
docdown/template_adapters/__init__.py
docdown/template_adapters/pystache.py
docdown/template_adapters/string_format.py
docdown/template_adapters/template_string.py
docdown-0.5.0.dist-info/METADATA
docdown-0.5.0.dist-info/WHEEL
docdown-0.5.0.dist-info/RECORD
